LICENSE
README.md
setup.py
dnn_locate/EDA.py
dnn_locate/__init__.py
dnn_locate/loc_model.py
dnn_locate.egg-info/PKG-INFO
dnn_locate.egg-info/SOURCES.txt
dnn_locate.egg-info/dependency_links.txt
dnn_locate.egg-info/requires.txt
dnn_locate.egg-info/top_level.txt