Metadata-Version: 2.1
Name: dnn-locate
Version: 0.2
Summary: dnn-locate is a Python module for discriminative features localization based on neural networks.
Home-page: https://github.com/statmlben/dnn-locate
Author: ['Ben Dai']
Author-email: bendai@cuhk.edu.hk
License: MIT
Platform: UNKNOWN
License-File: LICENSE
